union_runtime/__init__.py
union_runtime/_logging.py
union_runtime/_bin/__init__.py
union_runtime/_bin/serve.py
union_runtime/_download/__init__.py
union_runtime/_download/byoc.py
union_runtime/_download/serverless/__init__.py
union_runtime/_download/serverless/_async_files.py
union_runtime/_download/serverless/_channel.py
union_runtime/_download/serverless/_middleware.py
union_runtime/_internal/common/list_pb2.py
union_runtime/_internal/common/list_pb2.pyi
union_runtime/_internal/common/list_pb2_grpc.py
union_runtime/_internal/objectstore/definition_pb2.py
union_runtime/_internal/objectstore/definition_pb2.pyi
union_runtime/_internal/objectstore/definition_pb2_grpc.py
union_runtime/_internal/objectstore/metadata_service_pb2.py
union_runtime/_internal/objectstore/metadata_service_pb2.pyi
union_runtime/_internal/objectstore/metadata_service_pb2_grpc.py
union_runtime/_internal/objectstore/objectstore_service_pb2.py
union_runtime/_internal/objectstore/objectstore_service_pb2.pyi
union_runtime/_internal/objectstore/objectstore_service_pb2_grpc.py
union_runtime/_internal/objectstore/payload_pb2.py
union_runtime/_internal/objectstore/payload_pb2.pyi
union_runtime/_internal/objectstore/payload_pb2_grpc.py
union_runtime/_internal/validate/validate/validate_pb2.py
union_runtime/_internal/validate/validate/validate_pb2_grpc.py
union_runtime/_lib/__init__.py
union_runtime/_lib/constants.py
union_runtime/_lib/inputs.py
union_runtime-0.1.18.dist-info/licenses/LICENSE
union_runtime-0.1.18.dist-info/licenses/licenses/APL.txt
union_runtime-0.1.18.dist-info/licenses/licenses/BSL.txt
union_runtime-0.1.18.dist-info/METADATA
union_runtime-0.1.18.dist-info/WHEEL
union_runtime-0.1.18.dist-info/entry_points.txt
union_runtime-0.1.18.dist-info/top_level.txt
union_runtime-0.1.18.dist-info/RECORD
